sudoblark_python_core/__init__.py
sudoblark_python_core/abstracts/__init__.py
sudoblark_python_core/abstracts/restapi.py
sudoblark_python_core/github/__init__.py
sudoblark_python_core/github/client.py
sudoblark_python_core/github/comments.py
sudoblark_python_core/github/organisation.py
sudoblark_python_core/github/pull_request.py
sudoblark_python_core/github/repository.py
sudoblark_python_core-1.0.2.dist-info/LICENSE.txt
sudoblark_python_core-1.0.2.dist-info/METADATA
sudoblark_python_core-1.0.2.dist-info/WHEEL
sudoblark_python_core-1.0.2.dist-info/RECORD
