Metadata-Version: 2.3
Name: sudoblark-python-core
Version: 1.0.2
Summary: Core python library for Sudoblark.
License: BSD-3
Author: Ben Clark
Author-email: bclark@sudoblark.com
Requires-Python: >=3.10.0,<4.0
Classifier: License :: Other/Proprietary License
Classifier: Programming Language :: Python :: 3
Classifier: Programming Language :: Python :: 3.10
Classifier: Programming Language :: Python :: 3.11
Classifier: Programming Language :: Python :: 3.12
Classifier: Programming Language :: Python :: 3.13
Classifier: Topic :: Software Development :: Libraries :: Python Modules
Requires-Dist: requests (>=2.32.3,<3.0.0)
Project-URL: Repository, https://github.com/sudoblark/sudoblark.python.core
